<?xml version="1.0" encoding="utf-8" ?>
<dwsync>
<file name="desktop.ini" server="sftp.ucsc.edu//afs/cats.ucsc.edu/www/vaw/" local="131713647560000000" remote="131713647560000000" Dst="2" />
<file name="fullcalendar.min.js" server="sftp.ucsc.edu//afs/cats.ucsc.edu/www/vaw/" local="131713647560000000" remote="131713647560000000" Dst="2" />
<file name="fullcalendar.print.min.css" server="sftp.ucsc.edu//afs/cats.ucsc.edu/www/vaw/" local="131713647560000000" remote="131713647560000000" Dst="2" />
<file name="gallery.js" server="sftp.ucsc.edu//afs/cats.ucsc.edu/www/vaw/" local="131713647560000000" remote="131713647560000000" Dst="2" />
<file name="gcal.min.js" server="sftp.ucsc.edu//afs/cats.ucsc.edu/www/vaw/" local="131713647560000000" remote="131713647560000000" Dst="2" />
<file name="jquery-2.1.1.js" server="sftp.ucsc.edu//afs/cats.ucsc.edu/www/vaw/" local="131713647560000000" remote="131713647560000000" Dst="2" />
<file name="jquery-3.2.1.js" server="sftp.ucsc.edu//afs/cats.ucsc.edu/www/vaw/" local="131713647560000000" remote="131713647560000000" Dst="2" />
<file name="jquery.mobile.custom.min.js" server="sftp.ucsc.edu//afs/cats.ucsc.edu/www/vaw/" local="131713647560000000" remote="131713647560000000" Dst="2" />
<file name="jquery.nanogallery2.js" server="sftp.ucsc.edu//afs/cats.ucsc.edu/www/vaw/" local="131713647570000000" remote="131713647570000000" Dst="2" />
<file name="main.js" server="sftp.ucsc.edu//afs/cats.ucsc.edu/www/vaw/" local="131713647570000000" remote="131713647570000000" Dst="2" />
<file name="modernizr.js" server="sftp.ucsc.edu//afs/cats.ucsc.edu/www/vaw/" local="131713647570000000" remote="131713647570000000" Dst="2" />
<file name="moment.js" server="sftp.ucsc.edu//afs/cats.ucsc.edu/www/vaw/" local="131713647570000000" remote="131713647570000000" Dst="2" />
<file name="skel.min.js" server="sftp.ucsc.edu//afs/cats.ucsc.edu/www/vaw/" local="131713647570000000" remote="131713647570000000" Dst="2" />
<file name="slideshow.js" server="sftp.ucsc.edu//afs/cats.ucsc.edu/www/vaw/" local="131713647570000000" remote="131713647570000000" Dst="2" />
<file name="suwa.js" server="sftp.ucsc.edu//afs/cats.ucsc.edu/www/vaw/" local="131713647570000000" remote="131713647570000000" Dst="2" />
<file name="util.js" server="sftp.ucsc.edu//afs/cats.ucsc.edu/www/vaw/" local="131713647570000000" remote="131713647570000000" Dst="2" />
<file name="desktop.ini" server="sftp.ucsc.edu//afs/cats.ucsc.edu/www/vaw/prod/public_html/" local="131713647560000000" remote="131715889010000000" Dst="2" />
<file name="fullcalendar.min.js" server="sftp.ucsc.edu//afs/cats.ucsc.edu/www/vaw/prod/public_html/" local="131713647560000000" remote="131715889010000000" Dst="2" />
<file name="fullcalendar.print.min.css" server="sftp.ucsc.edu//afs/cats.ucsc.edu/www/vaw/prod/public_html/" local="131713647560000000" remote="131715889010000000" Dst="2" />
<file name="gallery.js" server="sftp.ucsc.edu//afs/cats.ucsc.edu/www/vaw/prod/public_html/" local="131713647560000000" remote="131715889010000000" Dst="2" />
<file name="gcal.min.js" server="sftp.ucsc.edu//afs/cats.ucsc.edu/www/vaw/prod/public_html/" local="131713647560000000" remote="131715889010000000" Dst="2" />
<file name="jquery-2.1.1.js" server="sftp.ucsc.edu//afs/cats.ucsc.edu/www/vaw/prod/public_html/" local="131713647560000000" remote="131715889010000000" Dst="2" />
<file name="jquery-3.2.1.js" server="sftp.ucsc.edu//afs/cats.ucsc.edu/www/vaw/prod/public_html/" local="131713647560000000" remote="131715889010000000" Dst="2" />
<file name="jquery.mobile.custom.min.js" server="sftp.ucsc.edu//afs/cats.ucsc.edu/www/vaw/prod/public_html/" local="131713647560000000" remote="131715889010000000" Dst="2" />
<file name="jquery.nanogallery2.js" server="sftp.ucsc.edu//afs/cats.ucsc.edu/www/vaw/prod/public_html/" local="131713647570000000" remote="131715889010000000" Dst="2" />
<file name="main.js" server="sftp.ucsc.edu//afs/cats.ucsc.edu/www/vaw/prod/public_html/" local="131713647570000000" remote="131715889010000000" Dst="2" />
<file name="modernizr.js" server="sftp.ucsc.edu//afs/cats.ucsc.edu/www/vaw/prod/public_html/" local="131713647570000000" remote="131715889010000000" Dst="2" />
<file name="moment.js" server="sftp.ucsc.edu//afs/cats.ucsc.edu/www/vaw/prod/public_html/" local="131713647570000000" remote="131715889010000000" Dst="2" />
<file name="skel.min.js" server="sftp.ucsc.edu//afs/cats.ucsc.edu/www/vaw/prod/public_html/" local="131713647570000000" remote="131715889010000000" Dst="2" />
<file name="slideshow.js" server="sftp.ucsc.edu//afs/cats.ucsc.edu/www/vaw/prod/public_html/" local="131713647570000000" remote="131715889010000000" Dst="2" />
<file name="suwa.js" server="sftp.ucsc.edu//afs/cats.ucsc.edu/www/vaw/prod/public_html/" local="131713647570000000" remote="131715889010000000" Dst="2" />
<file name="util.js" server="sftp.ucsc.edu//afs/cats.ucsc.edu/www/vaw/prod/public_html/" local="131713647570000000" remote="131715889010000000" Dst="2" />
</dwsync>